{
  "items" : [ {
    "track" : {
      "album" : {
        "name" : "ANTI"
      },
      "artists" : [ {
        "name" : "Rihanna"
      } ],
      "duration_ms" : 191600,
      "explicit" : true,
      "name" : "Needed Me",
      "popularity" : 90
    }
  }, {
    "track" : {
      "album" : {
        "name" : "oui"
      },
      "artists" : [ {
        "name" : "Jeremih"
      } ],
      "duration_ms" : 238480,
      "explicit" : false,
      "name" : "oui",
      "popularity" : 36
    }
  }, {
    "track" : {
      "album" : {
        "name" : "No Limit"
      },
      "artists" : [ {
        "name" : "Usher"
      }, {
        "name" : "Young Thug"
      } ],
      "duration_ms" : 228905,
      "explicit" : true,
      "name" : "No Limit",
      "popularity" : 65
    }
  }, {
    "track" : {
      "album" : {
        "name" : "You Should Be Here"
      },
      "artists" : [ {
        "name" : "Kehlani"
      }, {
        "name" : "Chance The Rapper"
      } ],
      "duration_ms" : 262520,
      "explicit" : true,
      "name" : "The Way (feat. Chance the Rapper)",
      "popularity" : 72
    }
  }, {
    "track" : {
      "album" : {
        "name" : "Don't"
      },
      "artists" : [ {
        "name" : "Bryson Tiller"
      } ],
      "duration_ms" : 200213,
      "explicit" : true,
      "name" : "Don't",
      "popularity" : 75
    }
  }, {
    "track" : {
      "album" : {
        "name" : "Come and See Me (feat. Drake)"
      },
      "artists" : [ {
        "name" : "PARTYNEXTDOOR"
      }, {
        "name" : "Drake"
      } ],
      "duration_ms" : 235477,
      "explicit" : true,
      "name" : "Come and See Me (feat. Drake)",
      "popularity" : 82
    }
  }, {
    "track" : {
      "album" : {
        "name" : "Simple Things (Remix)"
      },
      "artists" : [ {
        "name" : "Miguel"
      }, {
        "name" : "Chris Brown"
      }, {
        "name" : "Future"
      } ],
      "duration_ms" : 237797,
      "explicit" : true,
      "name" : "Simple Things (Remix)",
      "popularity" : 75
    }
  }, {
    "track" : {
      "album" : {
        "name" : "Ride Of Your Life"
      },
      "artists" : [ {
        "name" : "Tinashe"
      } ],
      "duration_ms" : 213828,
      "explicit" : true,
      "name" : "Ride Of Your Life",
      "popularity" : 69
    }
  }, {
    "track" : {
      "album" : {
        "name" : "Valet (feat. Fetty Wap and 2 Chainz)"
      },
      "artists" : [ {
        "name" : "Eric Bellinger"
      }, {
        "name" : "2 Chainz"
      }, {
        "name" : "Fetty Wap"
      } ],
      "duration_ms" : 204324,
      "explicit" : true,
      "name" : "Valet (feat. Fetty Wap and 2 Chainz)",
      "popularity" : 75
    }
  }, {
    "track" : {
      "album" : {
        "name" : "Wishing (feat. Chris Brown, Skeme & Lyquin)"
      },
      "artists" : [ {
        "name" : "DJ Drama"
      }, {
        "name" : "Chris Brown"
      }, {
        "name" : "Skeme"
      }, {
        "name" : "Lyquin"
      } ],
      "duration_ms" : 252306,
      "explicit" : true,
      "name" : "Wishing (feat. Chris Brown, Skeme & Lyquin)",
      "popularity" : 72
    }
  }, {
    "track" : {
      "album" : {
        "name" : "Beauty Behind The Madness"
      },
      "artists" : [ {
        "name" : "The Weeknd"
      } ],
      "duration_ms" : 348853,
      "explicit" : true,
      "name" : "Acquainted",
      "popularity" : 73
    }
  }, {
    "track" : {
      "album" : {
        "name" : "T R A P S O U L"
      },
      "artists" : [ {
        "name" : "Bryson Tiller"
      } ],
      "duration_ms" : 194613,
      "explicit" : true,
      "name" : "Exchange",
      "popularity" : 84
    }
  }, {
    "track" : {
      "album" : {
        "name" : "Crush"
      },
      "artists" : [ {
        "name" : "Yuna"
      }, {
        "name" : "Usher"
      } ],
      "duration_ms" : 241493,
      "explicit" : false,
      "name" : "Crush",
      "popularity" : 33
    }
  }, {
    "track" : {
      "album" : {
        "name" : "Late Nights: The Album"
      },
      "artists" : [ {
        "name" : "Jeremih"
      }, {
        "name" : "Ty Dolla $ign"
      } ],
      "duration_ms" : 245520,
      "explicit" : true,
      "name" : "Impatient",
      "popularity" : 72
    }
  }, {
    "track" : {
      "album" : {
        "name" : "Keep You in Mind"
      },
      "artists" : [ {
        "name" : "Guordan Banks"
      } ],
      "duration_ms" : 195996,
      "explicit" : false,
      "name" : "Keep You in Mind",
      "popularity" : 67
    }
  }, {
    "track" : {
      "album" : {
        "name" : "Back To Sleep REMIX"
      },
      "artists" : [ {
        "name" : "Chris Brown"
      }, {
        "name" : "Usher"
      }, {
        "name" : "ZAYN"
      } ],
      "duration_ms" : 267156,
      "explicit" : true,
      "name" : "Back To Sleep REMIX",
      "popularity" : 74
    }
  }, {
    "track" : {
      "album" : {
        "name" : "1990x"
      },
      "artists" : [ {
        "name" : "Maxwell"
      } ],
      "duration_ms" : 284693,
      "explicit" : false,
      "name" : "1990x",
      "popularity" : 61
    }
  }, {
    "track" : {
      "album" : {
        "name" : "Hallelujah"
      },
      "artists" : [ {
        "name" : "Alicia Keys"
      } ],
      "duration_ms" : 189337,
      "explicit" : false,
      "name" : "Hallelujah",
      "popularity" : 62
    }
  }, {
    "track" : {
      "album" : {
        "name" : "In The Room: Weight in Gold (feat. Seal)"
      },
      "artists" : [ {
        "name" : "Gallant"
      }, {
        "name" : "Seal"
      } ],
      "duration_ms" : 205726,
      "explicit" : false,
      "name" : "Weight in Gold (feat. Seal)",
      "popularity" : 63
    }
  }, {
    "track" : {
      "album" : {
        "name" : "LUV"
      },
      "artists" : [ {
        "name" : "Tory Lanez"
      } ],
      "duration_ms" : 228026,
      "explicit" : true,
      "name" : "LUV",
      "popularity" : 71
    }
  }, {
    "track" : {
      "album" : {
        "name" : "Sex Love & Pain II"
      },
      "artists" : [ {
        "name" : "Tank"
      }, {
        "name" : "Yo Gotti"
      } ],
      "duration_ms" : 318506,
      "explicit" : true,
      "name" : "I Love Ya (feat. Yo Gotti)",
      "popularity" : 64
    }
  }, {
    "track" : {
      "album" : {
        "name" : "Milestone"
      },
      "artists" : [ {
        "name" : "Chrisette Michele"
      }, {
        "name" : "Rick Ross"
      } ],
      "duration_ms" : 178464,
      "explicit" : false,
      "name" : "Equal",
      "popularity" : 51
    }
  }, {
    "track" : {
      "album" : {
        "name" : "In My Mind"
      },
      "artists" : [ {
        "name" : "BJ The Chicago Kid"
      } ],
      "duration_ms" : 269173,
      "explicit" : false,
      "name" : "Turnin' Me Up",
      "popularity" : 60
    }
  }, {
    "track" : {
      "album" : {
        "name" : "Crash"
      },
      "artists" : [ {
        "name" : "Usher"
      } ],
      "duration_ms" : 211375,
      "explicit" : false,
      "name" : "Crash",
      "popularity" : 73
    }
  }, {
    "track" : {
      "album" : {
        "name" : "TWENTY88"
      },
      "artists" : [ {
        "name" : "TWENTY88"
      } ],
      "duration_ms" : 269240,
      "explicit" : false,
      "name" : "London Bridge",
      "popularity" : 65
    }
  }, {
    "track" : {
      "album" : {
        "name" : "In Common"
      },
      "artists" : [ {
        "name" : "Alicia Keys"
      } ],
      "duration_ms" : 209050,
      "explicit" : false,
      "name" : "In Common",
      "popularity" : 78
    }
  }, {
    "track" : {
      "album" : {
        "name" : "The Heart Speaks In Whispers (Deluxe)"
      },
      "artists" : [ {
        "name" : "Corinne Bailey Rae"
      } ],
      "duration_ms" : 351226,
      "explicit" : false,
      "name" : "Green Aphrodisiac",
      "popularity" : 59
    }
  }, {
    "track" : {
      "album" : {
        "name" : "Lake By the Ocean"
      },
      "artists" : [ {
        "name" : "Maxwell"
      } ],
      "duration_ms" : 239026,
      "explicit" : false,
      "name" : "Lake By the Ocean",
      "popularity" : 66
    }
  }, {
    "track" : {
      "album" : {
        "name" : "Contradiction"
      },
      "artists" : [ {
        "name" : "Mali Music"
      }, {
        "name" : "Jhene Aiko"
      } ],
      "duration_ms" : 239813,
      "explicit" : false,
      "name" : "Contradiction",
      "popularity" : 66
    }
  }, {
    "track" : {
      "album" : {
        "name" : "ELDORADO"
      },
      "artists" : [ {
        "name" : "Ro James"
      } ],
      "duration_ms" : 216560,
      "explicit" : false,
      "name" : "Burn Slow",
      "popularity" : 60
    }
  }, {
    "track" : {
      "album" : {
        "name" : "Did I"
      },
      "artists" : [ {
        "name" : "Kehlani"
      } ],
      "duration_ms" : 215556,
      "explicit" : true,
      "name" : "Did I",
      "popularity" : 68
    }
  }, {
    "track" : {
      "album" : {
        "name" : "ANTI"
      },
      "artists" : [ {
        "name" : "Rihanna"
      }, {
        "name" : "Drake"
      } ],
      "duration_ms" : 219320,
      "explicit" : false,
      "name" : "Work",
      "popularity" : 68
    }
  }, {
    "track" : {
      "album" : {
        "name" : "Free TC"
      },
      "artists" : [ {
        "name" : "Ty Dolla $ign"
      }, {
        "name" : "E-40"
      } ],
      "duration_ms" : 178506,
      "explicit" : true,
      "name" : "Saved (feat. E-40)",
      "popularity" : 79
    }
  }, {
    "track" : {
      "album" : {
        "name" : "In My Feelings"
      },
      "artists" : [ {
        "name" : "Trevor Jackson"
      }, {
        "name" : "Iamsu!"
      } ],
      "duration_ms" : 204631,
      "explicit" : false,
      "name" : "Rock Wit Me (feat. IAMSU!)",
      "popularity" : 73
    }
  }, {
    "track" : {
      "album" : {
        "name" : "Too Deep"
      },
      "artists" : [ {
        "name" : "dvsn"
      } ],
      "duration_ms" : 199834,
      "explicit" : false,
      "name" : "Too Deep",
      "popularity" : 29
    }
  }, {
    "track" : {
      "album" : {
        "name" : "#BDAY (feat. Chris Brown, Siya, and Sage The Gemini)"
      },
      "artists" : [ {
        "name" : "Tank"
      }, {
        "name" : "Siya"
      }, {
        "name" : "Chris Brown"
      }, {
        "name" : "Sage The Gemini"
      } ],
      "duration_ms" : 312026,
      "explicit" : true,
      "name" : "#BDAY (feat. Chris Brown, Siya and Sage The Gemini)",
      "popularity" : 64
    }
  }, {
    "track" : {
      "album" : {
        "name" : "But You Caint Use My Phone (Mixtape)"
      },
      "artists" : [ {
        "name" : "Erykah Badu"
      } ],
      "duration_ms" : 208719,
      "explicit" : false,
      "name" : "Phone Down",
      "popularity" : 60
    }
  }, {
    "track" : {
      "album" : {
        "name" : "Sleeping With The One I Love"
      },
      "artists" : [ {
        "name" : "Fantasia"
      } ],
      "duration_ms" : 304176,
      "explicit" : false,
      "name" : "Sleeping With The One I Love",
      "popularity" : 57
    }
  }, {
    "track" : {
      "album" : {
        "name" : "Charlene"
      },
      "artists" : [ {
        "name" : "Tweet"
      }, {
        "name" : "Missy Elliott"
      } ],
      "duration_ms" : 260520,
      "explicit" : false,
      "name" : "Somebody Else Will (feat. Missy Elliott)",
      "popularity" : 60
    }
  }, {
    "track" : {
      "album" : {
        "name" : "More Issues Than Vogue"
      },
      "artists" : [ {
        "name" : "K. Michelle"
      } ],
      "duration_ms" : 254613,
      "explicit" : true,
      "name" : "Ain't You",
      "popularity" : 62
    }
  }, {
    "track" : {
      "album" : {
        "name" : "Hypnotizing"
      },
      "artists" : [ {
        "name" : "Aaron Camper"
      } ],
      "duration_ms" : 331500,
      "explicit" : true,
      "name" : "Hypnotizing",
      "popularity" : 62
    }
  }, {
    "track" : {
      "album" : {
        "name" : "Whatever Happened"
      },
      "artists" : [ {
        "name" : "Elijah Blake"
      } ],
      "duration_ms" : 279382,
      "explicit" : false,
      "name" : "Whatever Happened",
      "popularity" : 57
    }
  }, {
    "track" : {
      "album" : {
        "name" : "You Don't Know (feat. Wale)"
      },
      "artists" : [ {
        "name" : "Tank"
      }, {
        "name" : "Wale"
      } ],
      "duration_ms" : 246072,
      "explicit" : true,
      "name" : "You Don't Know (feat. Wale)",
      "popularity" : 56
    }
  }, {
    "track" : {
      "album" : {
        "name" : "Amen"
      },
      "artists" : [ {
        "name" : "Anthony Hamilton"
      } ],
      "duration_ms" : 218430,
      "explicit" : false,
      "name" : "Amen",
      "popularity" : 62
    }
  }, {
    "track" : {
      "album" : {
        "name" : "I Do"
      },
      "artists" : [ {
        "name" : "Musiq Soulchild"
      } ],
      "duration_ms" : 257773,
      "explicit" : false,
      "name" : "I Do",
      "popularity" : 63
    }
  }, {
    "track" : {
      "album" : {
        "name" : "Permission"
      },
      "artists" : [ {
        "name" : "Ro James"
      } ],
      "duration_ms" : 281511,
      "explicit" : true,
      "name" : "Permission",
      "popularity" : 68
    }
  }, {
    "track" : {
      "album" : {
        "name" : "Weak After Next Reloaded"
      },
      "artists" : [ {
        "name" : "Adrian Marcel"
      }, {
        "name" : "Raphael Saadiq"
      }, {
        "name" : "Big Snoop Dogg"
      } ],
      "duration_ms" : 255875,
      "explicit" : true,
      "name" : "SEARCHIN - Reloaded MIXTAPE",
      "popularity" : 60
    }
  }, {
    "track" : {
      "album" : {
        "name" : "Room In Here (feat. The Game & Sonyae Elise) - Single"
      },
      "artists" : [ {
        "name" : "Anderson Paak"
      }, {
        "name" : "The Game"
      }, {
        "name" : "Sonyae Elise"
      } ],
      "duration_ms" : 239173,
      "explicit" : true,
      "name" : "Room In Here",
      "popularity" : 56
    }
  }, {
    "track" : {
      "album" : {
        "name" : "You Mine"
      },
      "artists" : [ {
        "name" : "DJ Khaled"
      }, {
        "name" : "Trey Songz"
      }, {
        "name" : "Jeremih"
      }, {
        "name" : "Future"
      } ],
      "duration_ms" : 240026,
      "explicit" : false,
      "name" : "You Mine",
      "popularity" : 62
    }
  }, {
    "track" : {
      "album" : {
        "name" : "Hallucinations"
      },
      "artists" : [ {
        "name" : "dvsn"
      } ],
      "duration_ms" : 246293,
      "explicit" : false,
      "name" : "Hallucinations",
      "popularity" : 31
    }
  } ],
  "total" : 50
}